pyflo/__init__.py
pyflo/__to_remove_blockchain__.py
pyflo/address.py
pyflo/block.py
pyflo/consensus.py
pyflo/constants.py
pyflo/opcodes.py
pyflo/transaction.py
pyflo/wallet.py
pyflo/bip39_word_list/chinese_simplified.txt
pyflo/bip39_word_list/chinese_traditional.txt
pyflo/bip39_word_list/english.txt
pyflo/bip39_word_list/french.txt
pyflo/bip39_word_list/italian.txt
pyflo/bip39_word_list/japanese.txt
pyflo/bip39_word_list/korean.txt
pyflo/bip39_word_list/spanish.txt
pyflo/ellipticcurve/__init__.py
pyflo/ellipticcurve/curve.py
pyflo/ellipticcurve/ecdsa.py
pyflo/ellipticcurve/math.py
pyflo/ellipticcurve/point.py
pyflo/ellipticcurve/privateKey.py
pyflo/ellipticcurve/publicKey.py
pyflo/ellipticcurve/signature.py
pyflo/ellipticcurve/utils/__init__.py
pyflo/ellipticcurve/utils/binary.py
pyflo/ellipticcurve/utils/compatibility.py
pyflo/ellipticcurve/utils/der.py
pyflo/ellipticcurve/utils/file.py
pyflo/ellipticcurve/utils/integer.py
pyflo/ellipticcurve/utils/oid.py
pyflo/ellipticcurve/utils/pem.py
pyflo/functions/__init__.py
pyflo/functions/address.py
pyflo/functions/bip32.py
pyflo/functions/bip39_mnemonic.py
pyflo/functions/block.py
pyflo/functions/encode.py
pyflo/functions/hash.py
pyflo/functions/key.py
pyflo/functions/script.py
pyflo/functions/tools.py
pyflo/test/__init__.py
pyflo/test/address_class.py
pyflo/test/address_functions.py
pyflo/test/block.py
pyflo/test/create_transaction.py
pyflo/test/ecdsa.py
pyflo/test/hash_functions.py
pyflo/test/integer.py
pyflo/test/mnemonic.py
pyflo/test/raw_block.txt
pyflo/test/script_deserialize.py
pyflo/test/script_functions.py
pyflo/test/sighash.py
pyflo/test/transaction_constructor.py
pyflo/test/transaction_deserialize.py
pyflo_lib-2.0.9.dist-info/LICENSE
pyflo_lib-2.0.9.dist-info/METADATA
pyflo_lib-2.0.9.dist-info/WHEEL
pyflo_lib-2.0.9.dist-info/top_level.txt
pyflo_lib-2.0.9.dist-info/RECORD
